{
  "date": "2026-07-04",
  "stock_uncle_insight": {
    "date_header": "7/4 法人與主力大戶主要買超股票",
    "buyer_groups": [
      {
        "group_title": "1. 外資大戶：狂掃金融與傳產，面板、晶圓雙雄先避險",
        "stocks": [
          {
            "stock_name": "聯電",
            "ticker": "2303",
            "description": "外資買超聯電 3.5 萬張，但投信跟自營卻在倒貨，這是在玩兩手策略嗎？國際晶片股有雜音，外資這波操作很耐人尋味，肖年仔別黑白猜。"
          },
          {
            "stock_name": "中石化",
            "ticker": "1314",
            "description": "連中石化這種傳產股都能進外資買超榜 3.4 萬張，這說明外資在找低基期、有題材的避風港，肖年仔，別只看熱門股，冷門股有時才是寶。"
          },
          {
            "stock_name": "凱基金",
            "ticker": "2883",
            "description": "凱基金被外資買超 2.4 萬張，金融股持續被外資青睞，這波資金流向很明顯，穩健型資金的選擇，肖年仔可以學著點。"
          },
          {
            "stock_name": "群創",
            "ticker": "3481",
            "description": "外資狂倒群創 5.7 萬張，面板股被外資倒貨倒得兇，肖年仔別去接刀啊！外資都跑了，你還想當韭菜嗎？"
          },
          {
            "stock_name": "友達",
            "ticker": "2409",
            "description": "友達也被外資賣超 2.2 萬張，面板雙雄一起被砍，外資對面板後市不看好，這波跌勢恐怕還沒完。"
          },
          {
            "stock_name": "台積電",
            "ticker": "2330",
            "description": "連台積電都被外資小幅賣超 1.2 萬張，雖然不多，但這訊號很清楚，外資在科技股上還是偏保守，肖年仔要小心。"
          }
        ]
      },
      {
        "group_title": "2. 投信大戶（本土國家隊）：作帳行情啟動，鎖碼AI供應鏈與金融",
        "stocks": [
          {
            "stock_name": "佳世達",
            "ticker": "2352",
            "description": "投信持續作帳，買超佳世達 5922 張，鎖碼AI相關供應鏈，這就是本土國家隊的慣性，肖年仔可以觀察看看，但要小心結帳壓力。"
          },
          {
            "stock_name": "第一金",
            "ticker": "2892",
            "description": "第一金被投信買超 5576 張，金融股也是投信的愛，穩健配置，這波法人都在找安全牌。"
          },
          {
            "stock_name": "長榮航",
            "ticker": "2618",
            "description": "長榮航被投信買超 4735 張，航空股旺季效應，投信也來卡位，肖年仔，有題材的股票才有人氣。"
          },
          {
            "stock_name": "緯創",
            "ticker": "3231",
            "description": "緯創這AI概念股，投信持續加碼 4536 張，看好後市，雖然國際晶片股有雜音，但本土法人還是對AI有信心。"
          },
          {
            "stock_name": "華邦電",
            "ticker": "2344",
            "description": "華邦電被投信倒貨 1.8 萬張，記憶體股短期壓力不小，肖年仔，投信在跑，你還在追嗎？"
          },
          {
            "stock_name": "聯電",
            "ticker": "2303",
            "description": "投信賣超聯電 1.2 萬張，跟外資在聯電上不同調，這就是多空分歧，肖年仔，這種股票要特別小心。"
          }
        ]
      },
      {
        "group_title": "3. 內資主力與實戶：避險買ETF，航運、金融也來湊熱鬧",
        "stocks": [
          {
            "stock_name": "富邦科技",
            "ticker": "0052",
            "description": "自營商買超富邦科技 3194 張，這擺明是買ETF避險，肖年仔，市場震盪時，跟著大戶買ETF是最安全的選擇。"
          },
          {
            "stock_name": "南亞科",
            "ticker": "2408",
            "description": "自營商買超南亞科 1719 張，是看好記憶體反彈還是避險？這種操作很難說，肖年仔，別黑白猜。"
          },
          {
            "stock_name": "兆豐金",
            "ticker": "2886",
            "description": "兆豐金被自營商買超 1519 張，金融股穩健，自營商也來分一杯羹，這就是市場資金的避風港。"
          },
          {
            "stock_name": "長榮航",
            "ticker": "2618",
            "description": "長榮航被自營商買超 1044 張，航運股有題材，自營商也來隔日沖一下，肖年仔，這種短線操作要眼明手快。"
          },
          {
            "stock_name": "群創",
            "ticker": "3481",
            "description": "自營商也跟著外資倒群創 1573 張，這波面板真的要小心，大戶都在跑，你還想當接刀俠嗎？"
          },
          {
            "stock_name": "聯電",
            "ticker": "2303",
            "description": "自營商也賣超聯電 645 張，跟投信同調，外資卻在買，肖年仔，這檔股票多空分歧，別輕易出手。"
          }
        ]
      }
    ],
    "strategies": [
      {
        "strategy_title": "策略一：高檔避險與資金避風港（金融、ETF）",
        "strategy_content": "肖年仔，你看外資狂掃金融股，自營商也買ETF，這擺明是市場震盪，大戶把資金轉往防禦性標的。美股晶片股下跌，台股科技股也受影響，資金自然流向穩健的金融股和指數型ETF避險。這就是大戶在找安全牌，你還在追高殺低嗎？"
      },
      {
        "strategy_title": "策略二：AI供應鏈作帳行情與題材點火",
        "strategy_content": "投信持續鎖碼AI相關供應鏈，如佳世達、緯創等，這很明顯是季底作帳的慣性。雖然國際新聞提到晶片股下跌，AI基礎設施有疑慮，但本土投信仍看好AI長線趨勢，趁拉回佈局。肖年仔，這就是國家隊在幫你點火，但也要小心結帳壓力。"
      },
      {
        "strategy_title": "策略三：傳產與航運的波段操作與旺季效應",
        "strategy_content": "外資買中石化、中鋼等傳產，投信和自營商也買長榮航、陽明，這顯示部分資金在尋找低基期或有旺季題材的標的。航運股受惠運價題材，傳產則可能被視為價值型投資。肖年仔，別只看科技股，傳產和航運有時也能給你驚喜。"
      },
      {
        "strategy_title": "策略四：晶片股多空分歧，主力操作謹慎",
        "strategy_content": "聯電外資大買，但投信和自營商卻大賣，這顯示法人對晶片股的看法出現分歧。國際新聞也提到晶片股下跌，AI基礎設施疑慮，大戶們在晶片股的操作上顯得非常謹慎，多空交戰激烈。肖年仔，這種多空不明的股票，別輕易接刀，看清楚再說。"
      }
    ],
    "summary": "肖年仔，市場多空交戰，外資避險買金融，投信作帳鎖AI，自營商買ETF，面板、晶片股多空分歧，別黑白買，看清楚主力動向再出手！",
    "top_brokerages_analysis": [
      {
        "branch_name": "美商高盛",
        "action": "買超 1.66 萬張",
        "uncle_logic": "高盛這外資大戶，狂掃台新新光金 1.66 萬張，擺明是看好金融股的防禦性跟下半年的獲利展望。肖年仔，這不是隔日沖，這是長線布局的訊號！"
      },
      {
        "branch_name": "凱基台北",
        "action": "買超 1277 張",
        "uncle_logic": "凱基台北這分點，買富邦科技 ETF 1277 張，這很明顯是短線避險盤，或是隔日沖的慣性。肖年仔，這種買法，明天可能就倒貨給你，別傻傻去接刀！"
      },
      {
        "branch_name": "元大投信",
        "action": "買超 2664 張",
        "uncle_logic": "元大投信買佳世達 2664 張，這就是標準的投信作帳行情。佳世達有AI題材，投信趁機拉抬，準備年底結算衝績效，肖年仔可以觀察看看，但要小心結帳壓力。"
      },
      {
        "branch_name": "摩根大通",
        "action": "賣超 1.73 萬張",
        "uncle_logic": "摩根大通這外資大戶，狂倒群創 1.73 萬張，跟外資整體賣超面板的趨勢一致。肖年仔，面板股現在是燙手山芋，外資在撤退，你還想去接刀當韭菜嗎？"
      }
    ]
  },
  "english_professor_news": [
    {
      "news_id": "news_1",
      "title": "Forget the Retail Tech Glitz: I Am Loading Up on This Unassailable Enterprise Cash Cow",
      "source": "Yahoo Finance",
      "link": "https://finance.yahoo.com/markets/stocks/articles/forget-retail-tech-glitz-am-151844766.html",
      "level1_blind": {
        "text": "MSFT's Azure grew 40% and AI revenue hit a $37 billion annualized run rate while the stock trades at just 19 times forward earnings.\n\nCapex nearly doubled to $31 billion, but operating cash flow grew 26% as Microsoft's customers fund the AI buildout in real time.\n\nThirteen board members bought shares during the June dip, and commercial backlog surged 99% to $627 billion, locking in years of contracted revenue.\n\nAct now: the analyst who called NVIDIA in 2010 just named his top 10 AI stocks — and Microsoft didn't make the cut. Grab the names FREE today.\n\nI keep hitting the buy button on Microsoft (NASDAQ:MSFT), and the June selloff only made me press it harder. When the tape dragged this stock down to $373 in June while the underlying business printed 18.3% revenue growth, my thesis stopped being a thesis and started feeling like a gift. I own this for the next twenty years of retirement income, through many cycles of noisy headlines.\n\nWhat pulls me back is boring in the best way. Microsoft sells the plumbing every enterprise on earth now depends on: Windows, Office 365, Azure, GitHub, Dynamics, LinkedIn. Companies do not rip that stack out during a recession. They renew it, expand it, and pay more for it every cycle. That is the cash-flow utility I want anchoring my portfolio.\n\nFirst, the operational reality is running in the opposite direction of the stock chart. Q3 FY26 delivered EPS of $4.27 against a $4.07 estimate, the fourth consecutive beat, on $82.89 billion in revenue. Intelligent Cloud grew 30%, Azure grew 40%, and the AI business now runs at a $37 billion annualized rate, up 123% year over year. Alpha Vantage shows 12 consecutive quarterly beats and an 83.8% beat rate across 130 quarters. That is a compounding machine.\n\nAct now: the analyst who called NVIDIA in 2010 just named his top 10 AI stocks — and Microsoft didn't make the cut. Grab the names FREE today."
      },
      "level2_keywords": [
        {
          "word": "Azure",
          "ipa": "/ˈæʒər/",
          "meaning": "各位同學，Azure 是微軟旗下的雲端運算服務平台，提供各種企業級的雲端解決方案，是微軟近年來成長最快的業務之一。",
          "example": "Microsoft's Azure cloud platform is a key driver of its impressive revenue growth and enterprise adoption."
        },
        {
          "word": "annualized run rate",
          "ipa": "/ˈænjuəlaɪzd rʌn reɪt/",
          "meaning": "這句話在財經界的意思是「年化運行速度」，指將某個時期的營收或獲利數據，推算成一整年的預估值，用來評估業務的成長動能。",
          "example": "The company's new AI services are now at a $37 billion annualized run rate, showing rapid expansion and market penetration."
        },
        {
          "word": "forward earnings",
          "ipa": "/ˈfɔːrwərd ˈɜːrnɪŋz/",
          "meaning": "我們要注意這個詞，它指的是「預期未來一年的每股盈餘」，是投資人評估股票價值時常用的指標，用來衡量股價相對於未來獲利的合理性。",
          "example": "Despite strong growth, the stock trades at a reasonable 19 times forward earnings, suggesting it's not overvalued in the current market."
        },
        {
          "word": "Capex",
          "ipa": "/ˈkeɪpɛks/",
          "meaning": "Capex 是 Capital Expenditure 的縮寫，也就是「資本支出」，指企業用於購買或升級固定資產的費用，例如廠房、設備或數據中心等，這些投資通常是為了未來的成長。",
          "example": "Despite a significant increase in Capex to build out its AI infrastructure, Microsoft's operating cash flow remains robust, indicating healthy financial management."
        },
        {
          "word": "commercial backlog",
          "ipa": "/kəˈmɜːrʃəl ˈbæklɒɡ/",
          "meaning": "這指的是「商業訂單積壓」，也就是企業已簽約但尚未完成交付的訂單總額。這個數字越高，通常代表企業未來營收的潛力越大，是衡量業務穩定性的重要指標。",
          "example": "A surging commercial backlog of $627 billion indicates strong future revenue for Microsoft for years to come, providing excellent visibility into its financial performance."
        }
      ],
      "level2_context": "各位同學，這篇新聞主要在探討為什麼微軟（Microsoft）在科技股中，被視為一個「穩健的現金牛」投資標的，尤其是在當前 AI 浪潮下。文章強調，儘管零售科技股可能光鮮亮麗，但微軟憑藉其核心的企業級軟體和雲端服務（特別是 Azure），展現出極強的韌性和成長潛力。即使在經濟下行或市場震盪時，企業對 Windows、Office 365、Azure 等基礎設施的需求依然強勁，甚至會持續續約和擴展使用，這為微軟帶來穩定且不斷增長的現金流。新聞也特別指出，微軟在 AI 領域的投資正快速轉化為實際營收，且其財務數據（如營運現金流、訂單積壓）表現亮眼，顯示公司在 AI 基礎建設上的投入正被客戶即時買單，這讓它成為一個值得長期持有的「退休金」級別資產。",
      "level3_translation": [
        {
          "sentence": "MSFT's Azure grew 40% and AI revenue hit a $37 billion annualized run rate while the stock trades at just 19 times forward earnings.",
          "translation": "微軟的 Azure 雲端服務成長了四成，AI 相關營收也達到每年 370 億美元的年化運行速度，而這檔股票目前的本益比僅有預期獲利的 19 倍。"
        },
        {
          "sentence": "Capex nearly doubled to $31 billion, but operating cash flow grew 26% as Microsoft's customers fund the AI buildout in real time.",
          "translation": "雖然資本支出幾乎翻倍來到 310 億美元，但由於微軟的客戶即時為其 AI 基礎建設買單，營運現金流仍成長了 26%。"
        },
        {
          "sentence": "Thirteen board members bought shares during the June dip, and commercial backlog surged 99% to $627 billion, locking in years of contracted revenue.",
          "translation": "今年六月股價下跌時，有 13 位董事會成員買進了股票，而且商業訂單積壓（commercial backlog）暴增了 99%，達到 6270 億美元，這鎖定了未來數年的合約營收。"
        },
        {
          "sentence": "Act now: the analyst who called NVIDIA in 2010 just named his top 10 AI stocks — and Microsoft didn't make the cut.",
          "translation": "立即行動：那位在 2010 年就精準預測到輝達（NVIDIA）的分析師，最近剛公布了他心目中的十大 AI 股票——但微軟卻沒有入選。"
        },
        {
          "sentence": "Grab the names FREE today.",
          "translation": "今天就免費取得這些股票名單吧！"
        },
        {
          "sentence": "I keep hitting the buy button on Microsoft (NASDAQ:MSFT), and the June selloff only made me press it harder.",
          "translation": "我持續買進微軟（NASDAQ:MSFT）的股票，而六月的這波拋售潮只讓我更堅定地加碼。"
        },
        {
          "sentence": "When the tape dragged this stock down to $373 in June while the underlying business printed 18.3% revenue growth, my thesis stopped being a thesis and started feeling like a gift.",
          "translation": "當市場在六月將這檔股票拖累到 373 美元，而其基本業務卻仍實現 18.3% 的營收成長時，我的投資論點就不再只是一個論點，而更像是一份禮物了。"
        },
        {
          "sentence": "I own this for the next twenty years of retirement income, through many cycles of noisy headlines.",
          "translation": "我持有這檔股票是為了未來二十年的退休收入，它將伴隨我度過許多喧囂的市場新聞週期。"
        },
        {
          "sentence": "What pulls me back is boring in the best way.",
          "translation": "吸引我的地方，是以一種最好的方式呈現的『無聊』。"
        },
        {
          "sentence": "Microsoft sells the plumbing every enterprise on earth now depends on: Windows, Office 365, Azure, GitHub, Dynamics, LinkedIn.",
          "translation": "微軟銷售的是全球每家企業現在都賴以生存的基礎設施：Windows、Office 365、Azure、GitHub、Dynamics、LinkedIn。"
        },
        {
          "sentence": "Companies do not rip that stack out during a recession.",
          "translation": "企業在經濟衰退期間並不會把這些核心系統淘汰掉。"
        },
        {
          "sentence": "They renew it, expand it, and pay more for it every cycle.",
          "translation": "他們會續約、擴展使用，並且在每個週期支付更多費用。"
        },
        {
          "sentence": "That is the cash-flow utility I want anchoring my portfolio.",
          "translation": "這就是我希望作為投資組合核心的『現金流公用事業』特性。"
        },
        {
          "sentence": "First, the operational reality is running in the opposite direction of the stock chart.",
          "translation": "首先，公司的營運實況與股價走勢呈現反向。"
        },
        {
          "sentence": "Q3 FY26 delivered EPS of $4.27 against a $4.07 estimate, the fourth consecutive beat, on $82.89 billion in revenue.",
          "translation": "2026 財年第三季，微軟實現了每股盈餘 4.27 美元，超越了預估的 4.07 美元，這是連續第四次超越預期，總營收達到 828.9 億美元。"
        },
        {
          "sentence": "Intelligent Cloud grew 30%, Azure grew 40%, and the AI business now runs at a $37 billion annualized rate, up 123% year over year.",
          "translation": "智慧雲端業務成長了三成，Azure 成長了四成，而 AI 業務目前正以 370 億美元的年化速度運行，年增率高達 123%。"
        },
        {
          "sentence": "Alpha Vantage shows 12 consecutive quarterly beats and an 83.8% beat rate across 130 quarters.",
          "translation": "Alpha Vantage 的數據顯示，微軟已經連續 12 個季度超越財測，在過去 130 個季度中，超越預期的比率高達 83.8%。"
        },
        {
          "sentence": "That is a compounding machine.",
          "translation": "這簡直就是一台『複利機器』。"
        },
        {
          "sentence": "Act now: the analyst who called NVIDIA in 2010 just named his top 10 AI stocks — and Microsoft didn't make the cut.",
          "translation": "立即行動：那位在 2010 年就精準預測到輝達（NVIDIA）的分析師，最近剛公布了他心目中的十大 AI 股票——但微軟卻沒有入選。"
        },
        {
          "sentence": "Grab the names FREE today.",
          "translation": "今天就免費取得這些股票名單吧！"
        }
      ]
    },
    {
      "news_id": "news_2",
      "title": "Stock Indexes Turn Mixed as Chipmakers Sink",
      "source": "Yahoo Finance",
      "link": "https://finance.yahoo.com/markets/stocks/articles/stock-indexes-turn-mixed-chipmakers-151823193.html",
      "level1_blind": {
        "text": "The S&P 500 Index ($SPX) (SPY) is up +0.10% today, the Dow Jones Industrial Average ($DOWI) (DIA) is up +0.85%, and the Nasdaq 100 Index ($IUXX) (QQQ) is down -0.92%. September E-mini S&P futures (ESU26) are up +0.08%, and September E-mini Nasdaq futures (NQU26) are down -1.03%.\n\nStock indexes are mixed today, with the S&P 500 posting a 2-week high and the Dow Jones Industrials posting a new all-time high. The broader market has support today after a slower-than-expected increase in US nonfarm payrolls knocked bond yields lower and bolstered speculation that the Fed will be unable to raise interest rates any time soon. US hiring slowed sharply in June and was revised lower in May even as the unemployment rate fell to a 1-year low.\n\nCEO Phong Le Bought 11,000 Shares of MicroStrategy Preferred Stock as STRC Hit All-Time Lows\n\nHowever, stock gains are muted today, and the Nasdaq 100 is in negative territory amid weakness in chipmakers and AI-infrastructure stocks for a second session. South Korea's Kospi Index fell more than -7% to a 3-week low, led by a plunge in SK Hynix and Samsung Electronics on renewed doubts over the sustainability of the AI buildout boom. The losses in South Korean chipmakers come amid negative carryover from Wednesday, when Meta Platforms said it plans to sell computing power, raising questions about excess AI capacity.\n\nUS Jun nonfarm payrolls rose +57,000, weaker than expectations of +113,000, and May nonfarm payrolls were revised lower to +129,000 from the originally reported +172,000. The Jun unemployment rate unexpectedly fell -0.1 to a 1-year low of 4.2%, signaling a stronger labor market than expectations of no change at 4.3%.\n\nUS Jan average hourly earnings rose +0.3% m/m and +3.5% y/y, right on expectations.\n\nUS weekly initial unemployment claims unexpectedly fell -1,000 to 215,000, showing a stronger labor market than expectations of an increase to 218,000.\n\nUS May factory orders fell -1.3% m/m, a smaller decline than expectations of -2.0% m/m. Also, May factory orders ex-transportation rose +1.9% m/m, stronger than expectations of +1.0% m/m and the biggest increase in more than 4 years."
      },
      "level2_keywords": [
        {
          "word": "nonfarm payrolls",
          "ipa": "/ˌnɑnˈfɑrm ˈpeɪˌroʊlz/",
          "meaning": "衡量美國非農業部門的就業人數變化，是判斷經濟健康狀況的重要指標。",
          "example": "「The latest nonfarm payrolls report showed a slower-than-expected increase, easing concerns about aggressive interest rate hikes.」"
        },
        {
          "word": "bond yields",
          "ipa": "/bɑnd jildz/",
          "meaning": "債券的投資報酬率，通常與利率和經濟前景密切相關。",
          "example": "「Slower hiring data knocked bond yields lower, suggesting investors anticipate less aggressive monetary tightening.」"
        },
        {
          "word": "chipmakers",
          "ipa": "/ˈtʃɪpˌmeɪkərz/",
          "meaning": "生產半導體晶片的廠商，是科技產業的核心。",
          "example": "「Weakness in chipmakers and AI-infrastructure stocks dragged down the Nasdaq 100 today.」"
        },
        {
          "word": "AI buildout boom",
          "ipa": "/ˌeɪ aɪ ˈbɪldˌaʊt bum/",
          "meaning": "指人工智慧基礎設施（如數據中心、AI晶片等）快速建設和擴張的熱潮。",
          "example": "「Renewed doubts over the sustainability of the AI buildout boom led to a plunge in major South Korean chipmakers.」"
        },
        {
          "word": "excess AI capacity",
          "ipa": "/ˈɛkˌsɛs ˌeɪ aɪ kəˈpæsəti/",
          "meaning": "指人工智慧運算能力或相關基礎設施的供給過剩，可能導致市場競爭加劇或投資回報率下降。",
          "example": "「Meta Platforms' plan to sell computing power raised questions about potential excess AI capacity in the market.」"
        }
      ],
      "level2_context": "「各位同學，這篇新聞的背景脈絡是這樣的：今天美國股市呈現一個『冰火兩重天』的局面。一方面，由於美國最新公布的非農就業數據增長不如預期，這通常被市場解讀為經濟可能放緩，進而降低了聯準會（Fed）短期內升息的壓力。這種預期讓債券殖利率走低，並為整體大盤，特別是標普500和道瓊工業指數帶來了支撐，甚至創下歷史新高。\n\n然而，另一方面，科技股和AI相關類股卻表現疲軟，拖累了那斯達克100指數。這背後的主要原因，是市場對AI產業的未來發展產生了新的疑慮。南韓的晶片製造商，例如SK海力士和三星電子，股價大幅下跌，就是因為投資人開始質疑『AI基礎設施建置熱潮』能否持續。更具體來說，Meta Platforms宣布計劃出售其運算能力，這讓市場開始思考，AI運算能力是否可能出現『供給過剩』的情況。如果AI基礎設施的擴張速度超過了實際需求，那麼相關晶片製造商和AI服務供應商的營收成長動能就可能受到影響，進而衝擊其股價表現。所以，這篇新聞反映了市場在宏觀經濟數據和特定產業前景之間，複雜的權衡與反應。」",
      "level3_translation": [
        {
          "sentence": "The S&P 500 Index ($SPX) (SPY) is up +0.10% today, the Dow Jones Industrial Average ($DOWI) (DIA) is up +0.85%, and the Nasdaq 100 Index ($IUXX) (QQQ) is down -0.92%.",
          "translation": "「標普500指數（$SPX）(SPY) 今天上漲了0.10%，道瓊工業平均指數（$DOWI）(DIA) 上漲了0.85%，而那斯達克100指數（$IUXX）(QQQ) 則下跌了0.92%。」"
        },
        {
          "sentence": "September E-mini S&P futures (ESU26) are up +0.08%, and September E-mini Nasdaq futures (NQU26) are down -1.03%.",
          "translation": "「九月份的E-mini標普期貨（ESU26）上漲了0.08%，而九月份的E-mini那斯達克期貨（NQU26）則下跌了1.03%。」"
        },
        {
          "sentence": "Stock indexes are mixed today, with the S&P 500 posting a 2-week high and the Dow Jones Industrials posting a new all-time high.",
          "translation": "「今天股市指數表現好壞參半，標普500指數創下兩週新高，道瓊工業指數更是達到歷史新高。」"
        },
        {
          "sentence": "The broader market has support today after a slower-than-expected increase in US nonfarm payrolls knocked bond yields lower and bolstered speculation that the Fed will be unable to raise interest rates any time soon.",
          "translation": "「在美國非農就業數據增長不如預期後，整體大盤今天獲得支撐，因為這使得債券殖利率走低，並強化了市場對於聯準會短期內將無法升息的預期。」"
        },
        {
          "sentence": "US hiring slowed sharply in June and was revised lower in May even as the unemployment rate fell to a 1-year low.",
          "translation": "「美國六月份的招聘活動顯著放緩，五月份的數據也被下修，儘管失業率降至一年來的最低點。」"
        },
        {
          "sentence": "CEO Phong Le Bought 11,000 Shares of MicroStrategy Preferred Stock as STRC Hit All-Time Lows",
          "translation": "「執行長Phong Le買入了11,000股MicroStrategy的特別股，當時STRC股價正處於歷史低點。」"
        },
        {
          "sentence": "However, stock gains are muted today, and the Nasdaq 100 is in negative territory amid weakness in chipmakers and AI-infrastructure stocks for a second session.",
          "translation": "「然而，今天的股市漲幅受到抑制，那斯達克100指數連續第二個交易日呈現負成長，主要受到晶片製造商和AI基礎設施類股走弱的影響。」"
        },
        {
          "sentence": "South Korea's Kospi Index fell more than -7% to a 3-week low, led by a plunge in SK Hynix and Samsung Electronics on renewed doubts over the sustainability of the AI buildout boom.",
          "translation": "「南韓KOSPI指數下跌超過7%，跌至三週低點，主要原因是市場對AI基礎設施建置熱潮能否持續產生新的疑慮，導致SK海力士和三星電子股價暴跌。」"
        },
        {
          "sentence": "The losses in South Korean chipmakers come amid negative carryover from Wednesday, when Meta Platforms said it plans to sell computing power, raising questions about excess AI capacity.",
          "translation": "「南韓晶片製造商的跌勢，也受到週三負面消息的延續影響，當時Meta Platforms表示計劃出售其運算能力，引發了市場對AI運算能力可能過剩的質疑。」"
        },
        {
          "sentence": "US Jun nonfarm payrolls rose +57,000, weaker than expectations of +113,000, and May nonfarm payrolls were revised lower to +129,000 from the originally reported +172,000.",
          "translation": "「美國六月份非農就業人數增加了57,000人，低於市場預期的113,000人；而五月份的非農就業人數也從最初報告的172,000人下修至129,000人。」"
        },
        {
          "sentence": "The Jun unemployment rate unexpectedly fell -0.1 to a 1-year low of 4.2%, signaling a stronger labor market than expectations of no change at 4.3%.",
          "translation": "「六月份失業率意外下降0.1個百分點，達到一年來的低點4.2%，這顯示勞動市場比預期中（預期維持在4.3%不變）更為強勁。」"
        },
        {
          "sentence": "US Jan average hourly earnings rose +0.3% m/m and +3.5% y/y, right on expectations.",
          "translation": "「美國一月份平均時薪月增0.3%，年增3.5%，符合市場預期。」"
        },
        {
          "sentence": "US weekly initial unemployment claims unexpectedly fell -1,000 to 215,000, showing a stronger labor market than expectations of an increase to 218,000.",
          "translation": "「美國每週初次申請失業救濟金人數意外減少1,000人，降至215,000人，顯示勞動市場比預期中（預期增加至218,000人）更為強勁。」"
        },
        {
          "sentence": "US May factory orders fell -1.3% m/m, a smaller decline than expectations of -2.0% m/m.",
          "translation": "「美國五月份工廠訂單月減1.3%，跌幅小於市場預期的2.0%。」"
        },
        {
          "sentence": "Also, May factory orders ex-transportation rose +1.9% m/m, stronger than expectations of +1.0% m/m and the biggest increase in more than 4 years.",
          "translation": "「此外，五月份扣除運輸設備的工廠訂單月增1.9%，表現優於市場預期的1.0%，也是四年多來最大的增幅。」"
        }
      ]
    },
    {
      "news_id": "news_3",
      "title": "This Global Utility Stock Looks Very Cheap Right Now as It Invests Nearly $2 Billion in the U.S. Energy Buildout",
      "source": "Yahoo Finance",
      "link": "https://finance.yahoo.com/energy/articles/global-utility-stock-looks-very-151738374.html",
      "level1_blind": {
        "text": "We're seeing a utilities boom like we haven't in quite some time. Indeed, since the rise of the internet, I don't think we've seen this many infrastructure and utilities companies in the limelight as we're seeing now.\n\nOne company that's starting to grab investor attention in a big way is National Grid (NGG), a U.K.-based electricity and gas utility company. Serving much of the United Kingdom, National Grid is a company that's not often on investors' radar screens, but that could mean that it's an interesting opportunity to consider.\n\nBack-to-Back Upgrades Signal Rising Institutional Support for FuelCell Energy Stock\n\nWhy is that, you might ask? Well, National Grid just announced a big move on Wednesday to invest $1.75 billion in a U.S. artificial intelligence (AI) power infrastructure company, supporting the data center buildout.\n\nLet's dive more into this deal and why NGG stock has been seeing so much volatility following the news.\n\nThis $1.75 billion deal is significant in that it signals to investors that global utility players want a piece of what the U.S. market has to offer. Indeed, the data center buildout that's happening in the U.S. (and around the world) will inevitably result in a surge of power demand.\n\nThe particular company National Grid is investing in is Joulent, a company that's currently looking to undertake a massive 2.67 gigawatt (GW) project in Texas. In combination with Chevron (CVX), which is part of the joint venture to put this project together, National Grid looks to increase its exposure to the U.S. market and grab a slice of the tech-driven power demand many investors are after.\n\nNotably, this project should benefit from its geographic proximity to cheaper natural gas in the Permian Basin. Additionally, the fact that Microsoft (MSFT) is the key player looking to ultimately utilize the power generated by this facility in a long-term contract means that the sorts of long-term cash flows this project looks to generate should be increasingly stable."
      },
      "level2_keywords": [
        {
          "word": "utilities",
          "ipa": "/juˈtɪlɪtiz/",
          "meaning": "公用事業（指提供水、電、瓦斯等基礎服務的公司或行業）",
          "example": "The government regulates essential utilities to ensure fair pricing for all citizens."
        },
        {
          "word": "infrastructure",
          "ipa": "/ˈɪnfrəˌstrʌktʃər/",
          "meaning": "基礎建設（指一個國家或地區的基礎設施，如道路、橋樑、電網、通訊系統等）",
          "example": "Investing in robust infrastructure is crucial for long-term economic growth and development."
        },
        {
          "word": "data center buildout",
          "ipa": "/ˈdeɪtə ˈsɛntər ˈbɪldˌaʊt/",
          "meaning": "資料中心建置（指大規模興建或擴建資料中心設施的過程）",
          "example": "The rapid expansion of artificial intelligence requires significant global data center buildout."
        },
        {
          "word": "joint venture",
          "ipa": "/dʒɔɪnt ˈvɛntʃər/",
          "meaning": "合資企業（兩家或多家公司共同出資、分享利潤和風險的商業合作模式）",
          "example": "They formed a joint venture to develop a new renewable energy project in the region."
        },
        {
          "word": "exposure",
          "ipa": "/ɪkˈspoʊʒər/",
          "meaning": "曝險/市場佔有率（指在特定市場、資產或風險中的參與程度或份額）",
          "example": "The company aims to increase its exposure to the rapidly growing Asian technology market."
        }
      ],
      "level2_context": "各位同學，這則新聞揭示了一個重要的產業趨勢：隨著人工智慧（AI）的爆炸性發展，全球對資料中心的需求飆升，這也連帶引爆了對電力的龐大需求。傳統上被視為穩定但成長緩慢的公用事業公司，現在看到了新的成長機會。這篇報導中的英國國家電網（National Grid）就是一個很好的例子，它決定大手筆投資美國的AI電力基礎設施公司，這不僅顯示了公用事業巨頭正積極轉型，也反映出美國市場在AI和資料中心建置上的領先地位。此外，新聞提到利用德州二疊紀盆地較便宜的天然氣，以及微軟的長期合約，這都說明了這些大型投資案在規劃時，會非常注重成本效益與未來現金流的穩定性，以確保長期獲利。這對我們理解全球能源轉型和科技產業的交叉影響非常關鍵。",
      "level3_translation": [
        {
          "sentence": "We're seeing a utilities boom like we haven't in quite some time.",
          "translation": "各位同學，我們正目睹一場前所未見的公用事業榮景。"
        },
        {
          "sentence": "Indeed, since the rise of the internet, I don't think we've seen this many infrastructure and utilities companies in the limelight as we're seeing now.",
          "translation": "確實，自從網路興起以來，我認為我們從未見過如此多的基礎建設和公用事業公司受到如此高度的關注。"
        },
        {
          "sentence": "One company that's starting to grab investor attention in a big way is National Grid (NGG), a U.K.-based electricity and gas utility company.",
          "translation": "其中一家正大幅吸引投資人目光的公司是英國的電力與天然氣公用事業公司『國家電網』（National Grid，股票代碼：NGG）。"
        },
        {
          "sentence": "Serving much of the United Kingdom, National Grid is a company that's not often on investors' radar screens, but that could mean that it's an interesting opportunity to consider.",
          "translation": "國家電網主要服務英國大部分地區，這家公司通常不太受到投資人關注，但這也可能意味著它是一個值得考慮的潛在投資機會。"
        },
        {
          "sentence": "Back-to-Back Upgrades Signal Rising Institutional Support for FuelCell Energy Stock",
          "translation": "（這段是原文中的一個小標題，與主文無關，但仍需翻譯）連續的評級上調，預示著機構對燃料電池能源公司股票的支持正在增加。"
        },
        {
          "sentence": "Why is that, you might ask?",
          "translation": "你可能會問，為什麼會這樣呢？"
        },
        {
          "sentence": "Well, National Grid just announced a big move on Wednesday to invest $1.75 billion in a U.S. artificial intelligence (AI) power infrastructure company, supporting the data center buildout.",
          "translation": "原來，國家電網剛在週三宣布了一項重大舉措，將投資 17.5 億美元給一家美國的人工智慧（AI）電力基礎設施公司，以支持資料中心的建置。"
        },
        {
          "sentence": "Let's dive more into this deal and why NGG stock has been seeing so much volatility following the news.",
          "translation": "讓我們更深入探討這筆交易，以及為何這項消息發布後，國家電網（NGG）的股價出現如此大的波動。"
        },
        {
          "sentence": "This $1.75 billion deal is significant in that it signals to investors that global utility players want a piece of what the U.S. market has to offer.",
          "translation": "這筆 17.5 億美元的交易意義重大，它向投資人表明，全球的公用事業巨頭都想分一杯羹，參與美國市場的發展機會。"
        },
        {
          "sentence": "Indeed, the data center buildout that's happening in the U.S. (and around the world) will inevitably result in a surge of power demand.",
          "translation": "確實，美國（乃至全球）正在進行的資料中心大規模建置，將不可避免地導致電力需求大幅飆升。"
        },
        {
          "sentence": "The particular company National Grid is investing in is Joulent, a company that's currently looking to undertake a massive 2.67 gigawatt (GW) project in Texas.",
          "translation": "國家電網投資的這家特定公司是 Joulent，它目前正計畫在德州承接一個高達 2.67 吉瓦（GW）的巨型專案。"
        },
        {
          "sentence": "In combination with Chevron (CVX), which is part of the joint venture to put this project together, National Grid looks to increase its exposure to the U.S. market and grab a slice of the tech-driven power demand many investors are after.",
          "translation": "國家電網與雪佛龍（Chevron，股票代碼：CVX）共同成立合資企業來推動這個專案，藉此希望增加其在美國市場的曝險，並搶佔許多投資人追逐的科技驅動型電力需求市場。"
        },
        {
          "sentence": "Notably, this project should benefit from its geographic proximity to cheaper natural gas in the Permian Basin.",
          "translation": "值得注意的是，這個專案將受益於其地理位置，因為它鄰近二疊紀盆地（Permian Basin）較便宜的天然氣供應。"
        },
        {
          "sentence": "Additionally, the fact that Microsoft (MSFT) is the key player looking to ultimately utilize the power generated by this facility in a long-term contract means that the sorts of long-term cash flows this project looks to generate should be increasingly stable.",
          "translation": "此外，微軟（Microsoft，股票代碼：MSFT）作為主要客戶，計畫透過長期合約最終使用該設施產生的電力，這意味著這個專案預期產生的長期現金流將會越來越穩定。"
        }
      ]
    }
  ],
  "market_linker_insight": {
    "market_connection": "根據 Yahoo Finance 的國際財經新聞，Microsoft 的 Azure 疁速成長和 AI 部門的年化收入達到 37 億美元，表明該公司的企業 Cash Cow 功能正在穩定下來。這些信息與台新新光金、富邦科技等股權的買賣動向有著密切的關係，因為 Microsoft 的業績對於資本市場具有重要影響力。因此，可以預料在未來，Microsoft 的業績會持續穩定，從而推動相關股權的價值上升。"
  }
}