{
  "date": "2026-06-20",
  "stock_uncle_insight": {
    "date_header": "6/20 法人與主力大戶主要買超股票",
    "buyer_groups": [
      {
        "group_title": "1. 外資大戶：狂掃航空與面板",
        "stocks": [
          {
            "stock_name": "長榮航",
            "ticker": "2618",
            "description": "外資瘋狂買超 10.2 萬張（已連續 7 日加碼），基期低且暑期旺季大爆發。"
          },
          {
            "stock_name": "友達",
            "ticker": "2409",
            "description": "外資買超 7.5 萬張、自營商也買超 1.09 萬張（主力券商買超第 1 名）。"
          },
          {
            "stock_name": "華航",
            "ticker": "2610",
            "description": "外資買超 2.1 萬張，同屬現成有業績支撐的暑期旅遊避風港。"
          }
        ]
      },
      {
        "group_title": "2. 投信大戶（本土國家隊）：鎖定金融與轉機股",
        "stocks": [
          {
            "stock_name": "聯電",
            "ticker": "2303",
            "description": "投信買超 1.95 萬張。有趣的是外資當天大賣聯電 4.5 萬張，形成本土大戶與ETF資金死守、對決外資的局面。"
          },
          {
            "stock_name": "第一金",
            "ticker": "2892",
            "description": "投信與官股買超 1.87 萬張，撐盤色彩濃厚。"
          },
          {
            "stock_name": "兆豐金",
            "ticker": "2886",
            "description": "投信買超 1.73 萬張，防禦性質高。"
          },
          {
            "stock_name": "台新金",
            "ticker": "2887",
            "description": "投信買超 1.09 萬張，持續布局金控合併題材。"
          },
          {
            "stock_name": "國巨",
            "ticker": "2327",
            "description": "投信建倉，看好被動元件低谷回溫。"
          },
          {
            "stock_name": "禾伸堂",
            "ticker": "3026",
            "description": "默默敲進，被動元件低基期防守盤。"
          }
        ]
      },
      {
        "group_title": "3. 內資主力與實戶：點火光學題材",
        "stocks": [
          {
            "stock_name": "大立光",
            "ticker": "3008",
            "description": "大漲重返 5000 元大關，CPO 新技術與 iPhone 換機潮預期發酵。"
          },
          {
            "stock_name": "先進光",
            "ticker": "3362",
            "description": "二線光學股集體飆漲停，內資主力短線拉抬氣勢磅礴。"
          },
          {
            "stock_name": "中揚光",
            "ticker": "6668",
            "description": "低檔噴出，主力在權值股整理時拉抬具備想像空間的題材股。"
          }
        ]
      }
    ],
    "strategies": [
      {
        "strategy_title": "策略一：高檔避險與資金避風港（金融、航空）",
        "strategy_content": "由於科技權值股（如台積電、聯發科、台達電）近期漲幅已大，加上美股費半重挫，外資與本土大戶在 6/17 選擇將資金撤出高風險的半導體，轉進『防禦型』與『受惠於暑期旺季』的標的。航空雙雄即將迎來第 3 季暑假旅遊及貨運旺季，屬於基期相對科技股低的選擇，因而成為外資大吸金池。而第一金、兆豐金等金融股，則是投信與國家隊在大盤重挫時慣用的『撐盤』工具，防禦性極佳。"
      },
      {
        "strategy_title": "策略二：低基期與高殖利率卡位（面板、成熟製程）",
        "strategy_content": "面板雙虎近期股價基期極低，在市場恐慌時，這類『跌無可跌』且具有資產價值的低基期股票，反而成為主力資金短線停泊、賺取反彈的避風港。成熟製程的聯電，雖然外資因全球半導體修正調節 4.5 萬張，但投信大戶持續瘋狂吸納，著眼於聯電下檔有配息與評價面支撐，形成內外資的劇烈籌碼角力。"
      },
      {
        "strategy_title": "策略三：新技術題材點火（光學 CPO 題材）",
        "strategy_content": "6/17 盤面上最強眼的亮點就是光學股。主要是市場傳出共同封裝光學（CPO）新技術題材發酵，加上蘋果 iPhone 換機潮預期。大戶在權值股整理時，最喜歡找這類『有故事、有想像空間』且剛從底部發動的題材股進行短線拉抬，成功帶動整體中小型光學股集體噴出。"
      }
    ],
    "summary": "大戶在 6/17 的操作邏輯非常明確：『棄高換低、防禦與題材並重』。他們利用科技權值股開低的恐慌感，順勢將資金調配到具備旺季效應 of 航空、避險的金融，以及具備新技術亮點的光學族群。",
    "top_brokerages_analysis": [
      {
        "branch_name": "凱基台北",
        "action": "買超 1.09 萬張",
        "uncle_logic": "凱基台北在友達大玩隔日沖，明天開盤衝高大單出貨的機會非常高，肖年仔不要傻傻去接刀被割韭菜。"
      },
      {
        "branch_name": "美商高盛",
        "action": "買超 3.5 萬張",
        "uncle_logic": "高盛幫外資波段基金代操，大買長榮航代表對暑期航空旺季買盤有中長線共識，這算有利多支撐。"
      },
      {
        "branch_name": "元大投信",
        "action": "買超 8000 張",
        "uncle_logic": "投信在聯電上大打防守戰，明顯是本土高股息ETF和波段資金在死守季線，支撐力道不俗。"
      }
    ]
  },
  "english_professor_news": [
    {
      "news_id": "news_1",
      "title": "US tightens chip exports to AI sector targeting advanced accelerators",
      "source": "Reuters",
      "link": "https://www.reuters.com/technology/us-tightens-chip-exports-ai-sector-targeting-advanced-accelerators-2026-06",
      "level1_blind": {
        "text": "The Biden administration on Thursday announced a sweeping set of new export controls designed to restrict China's access to advanced semiconductor technology and high-end artificial intelligence chip accelerators. The rules, which expand on restrictions implemented last October, are aimed at preventing the use of Western AI technology in military applications. According to the Department of Commerce, these measures are essential to protect national security interests. However, the restrictions are expected to have a significant impact on global chipmakers, particularly those designing high-performance GPUs and accelerators for data centers. Companies like Nvidia, AMD, and Intel will face tighter licensing requirements for shipping their products to specific regions. Industry analysts suggest this move will accelerate efforts by major tech hubs to build localized supply chains and design proprietary hardware alternatives."
      },
      "level2_keywords": [
        {
          "word": "export controls",
          "ipa": "/ˈɛkspɔːrt kənˈtroʊlz/",
          "meaning": "各位同學，『export controls』指的是政府為了國家安全、外交政策或經濟目的，對特定商品、技術或服務的出口進行限制或禁止。這在國際貿易和科技競爭中是個非常重要的工具。",
          "example": "「The US government imposed new export controls on advanced AI chips to China.」"
        },
        {
          "word": "semiconductor technology",
          "ipa": "/ˌsɛmiˈkɒndʌktər tɛkˈnɒlədʒi/",
          "meaning": "我們要注意這個詞組，『semiconductor technology』泛指用於製造積體電路（也就是我們常說的晶片）的技術。它是現代所有電子產品的核心，從手機到超級電腦都離不開它。",
          "example": "「Restricting access to cutting-edge semiconductor technology is a key part of the new policy.」"
        },
        {
          "word": "AI chip accelerators",
          "ipa": "/ˌeɪ aɪ tʃɪp ækˈsɛləreɪtərz/",
          "meaning": "這句話在財經界的意思是，『AI chip accelerators』是專門為加速人工智慧運算而設計的特殊晶片。它們能大幅提升機器學習和深度學習的效率，是AI發展的關鍵硬體。",
          "example": "「The new rules specifically target high-end AI chip accelerators used in data centers.」"
        },
        {
          "word": "military applications",
          "ipa": "/ˈmɪlɪtɛri ˌæplɪˈkeɪʃənz/",
          "meaning": "各位同學，『military applications』指的是技術或產品在軍事領域的用途。例如，AI晶片可以用於武器系統、情報分析或國防科技，這也是各國政府高度關注的點。",
          "example": "「The goal of the restrictions is to prevent advanced AI technology from being used in military applications.」"
        },
        {
          "word": "localized supply chains",
          "ipa": "/ˈloʊkəlaɪzd səˈplaɪ tʃeɪnz/",
          "meaning": "『localized supply chains』指的是將供應鏈的生產、採購和分銷環節盡可能地集中在單一國家或地區。這樣做是為了減少對外部供應商的依賴，降低地緣政治風險，提升供應鏈韌性。",
          "example": "「The new export controls are expected to accelerate efforts to build localized supply chains for critical components.」"
        }
      ],
      "level2_context": "各位同學，這篇新聞的背景是美國政府持續加強對中國科技發展的限制，特別是在先進半導體和人工智慧領域。美國擔心這些高科技晶片和技術可能被中國用於提升其軍事能力，對美國國家安全構成威脅。因此，拜登政府宣布了新的出口管制措施，擴大了去年十月實施的限制範圍，目的就是阻止西方最尖端的AI技術流入中國的軍事應用。\n\n這項政策對全球晶片產業影響深遠。像輝達（Nvidia）、超微（AMD）和英特爾（Intel）這些設計高效能GPU和AI加速器的公司，未來要將產品出口到特定地區，將面臨更嚴格的審查和許可要求。這不僅會影響這些公司的營收，也可能促使中國等主要科技中心加速發展自己的本土供應鏈，並設計替代性的硬體方案，長期來看可能改變全球半導體產業的格局。這不僅是貿易戰，更是科技霸權的競爭。",
      "level3_translation": [
        {
          "sentence": "The Biden administration on Thursday announced a sweeping set of new export controls designed to restrict China's access to advanced semiconductor technology and high-end artificial intelligence chip accelerators.",
          "translation": "拜登政府週四宣布了一系列全面性的新出口管制措施，目的在於限制中國取得先進半導體技術和高階人工智慧晶片加速器。"
        },
        {
          "sentence": "The rules, which expand on restrictions implemented last October, are aimed at preventing the use of Western AI technology in military applications.",
          "translation": "這些新規定是去年十月實施的限制措施的延伸，主要目標是阻止西方的人工智慧技術被用於軍事用途。"
        },
        {
          "sentence": "According to the Department of Commerce, these measures are essential to protect national security interests.",
          "translation": "根據美國商務部的說法，這些措施對於保護國家安全利益至關重要。"
        },
        {
          "sentence": "However, the restrictions are expected to have a significant impact on global chipmakers, particularly those designing high-performance GPUs and accelerators for data centers.",
          "translation": "然而，這些限制預計將對全球晶片製造商產生重大影響，尤其是那些為資料中心設計高效能圖形處理器（GPU）和加速器的公司。"
        },
        {
          "sentence": "Companies like Nvidia, AMD, and Intel will face tighter licensing requirements for shipping their products to specific regions.",
          "translation": "像輝達（Nvidia）、超微（AMD）和英特爾（Intel）這樣的公司，未來將面臨更嚴格的許可要求，才能將產品運往特定地區。"
        },
        {
          "sentence": "Industry analysts suggest this move will accelerate efforts by major tech hubs to build localized supply chains and design proprietary hardware alternatives.",
          "translation": "產業分析師指出，此舉將加速主要科技中心建立本土化供應鏈，並設計自有專屬硬體替代方案的努力。"
        }
      ]
    },
    {
      "news_id": "news_2",
      "title": "Tech stocks rally as inflation concerns ease globally",
      "source": "Bloomberg",
      "link": "https://www.bloomberg.com/news/articles/2026-06/tech-stocks-rally-as-inflation-concerns-ease-globally",
      "level1_blind": {
        "text": "Shares in major technology companies rallied across global stock markets on Friday as cooling inflation data from both the United States and Europe eased investor concerns about aggressive interest rate hikes. The broad-based technology index gained over two percent, led by semiconductor companies and software service providers. Economic reports showed that consumer price indexes rose at a slower pace than anticipated last month, suggesting that central bank monetary policy is successfully curbing inflation without triggering a severe recession. In Asian markets, tech-heavy exchanges in Taipei, Tokyo, and Seoul closed higher, tracking Wall Street's positive momentum. Analysts believe that if inflation continues to stabilize, central banks may pause their rate hikes later this year, creating a more favorable environment for high-growth tech companies."
      },
      "level2_keywords": [
        {
          "word": "rallied",
          "ipa": "/ˈrælid/",
          "meaning": "股價反彈、上漲",
          "example": "「在利好消息刺激下，這檔股票今天強勁反彈。」"
        },
        {
          "word": "cooling inflation",
          "ipa": "/ˈkuːlɪŋ ɪnˈfleɪʃən/",
          "meaning": "通貨膨脹降溫",
          "example": "「各國央行正努力透過緊縮政策來達成通膨降溫的目標。」"
        },
        {
          "word": "interest rate hikes",
          "ipa": "/ˈɪntrɪst reɪt haɪks/",
          "meaning": "升息、利率調升",
          "example": "「聯準會持續的升息，讓市場對經濟前景感到擔憂。」"
        },
        {
          "word": "monetary policy",
          "ipa": "/ˈmɑnɪˌtɛri ˈpɑləsi/",
          "meaning": "貨幣政策",
          "example": "「央行的貨幣政策對控制通膨和刺激經濟成長至關重要。」"
        },
        {
          "word": "consumer price index",
          "ipa": "[kənˈsuːmər praɪs ˈɪndɛks]",
          "meaning": "消費者物價指數 (CPI)",
          "example": "「上個月的消費者物價指數顯示，通膨壓力有所緩解。」"
        }
      ],
      "level2_context": "「各位同學，這篇新聞的背景脈絡是全球市場對通膨的擔憂正在緩解。過去一段時間，各國央行為了抑制高漲的通膨，不斷採取激進的升息措施，這對科技股這類需要大量資金投入、且對未來獲利預期敏感的公司來說，是很大的壓力。因為升息會提高借貸成本，並降低未來現金流的現值。\n\n然而，現在美國和歐洲的最新經濟數據顯示，通膨壓力似乎正在降溫，這讓投資人開始預期央行可能不會再那麼激進地升息，甚至可能在今年稍晚暫停升息。這種預期讓市場情緒轉趨樂觀，資金重新流向被視為『高成長』的科技股，推動了全球科技股的普遍上漲。這對科技產業來說是個好消息，因為更穩定的利率環境有助於企業的投資與擴張。」",
      "level3_translation": [
        {
          "sentence": "Shares in major technology companies rallied across global stock markets on Friday as cooling inflation data from both the United States and Europe eased investor concerns about aggressive interest rate hikes.",
          "translation": "「週五，全球主要科技公司的股價普遍上漲，因為美國和歐洲的通膨數據顯示降溫，緩解了投資人對央行激進升息的擔憂。」"
        },
        {
          "sentence": "The broad-based technology index gained over two percent, led by semiconductor companies and software service providers.",
          "translation": "「廣泛的科技股指數上漲超過百分之二，其中以半導體公司和軟體服務供應商的表現最為突出。」"
        },
        {
          "sentence": "Economic reports showed that consumer price indexes rose at a slower pace than anticipated last month, suggesting that central bank monetary policy is successfully curbing inflation without triggering a severe recession.",
          "translation": "「經濟報告指出，上個月的消費者物價指數（CPI）漲幅低於預期，這暗示著各國央行的貨幣政策正成功抑制通膨，同時沒有引發嚴重的經濟衰退。」"
        },
        {
          "sentence": "In Asian markets, tech-heavy exchanges in Taipei, Tokyo, and Seoul closed higher, tracking Wall Street's positive momentum.",
          "translation": "「在亞洲市場方面，台北、東京和首爾等科技股比重較高的交易所也跟隨華爾街的正面走勢，收盤時呈現上漲。」"
        },
        {
          "sentence": "Analysts believe that if inflation continues to stabilize, central banks may pause their rate hikes later this year, creating a more favorable environment for high-growth tech companies.",
          "translation": "「分析師認為，如果通膨持續穩定，各國央行可能會在今年稍晚暫停升息，這將為高成長的科技公司創造一個更有利的營運環境。」"
        }
      ]
    }
  ],
  "market_linker_insight": {
    "violence_connection": "今日台股數據與國際財經新聞的暴力聯結，揭示了外資在市場上「先知先覺」的驚人佈局。晨間數據顯示，外資大舉拋售台積電、聯電、聯發科及世芯-KY、創意等AI晶片設計服務指標股，其規模之大，令人側目。隨後，下午國際財經新聞便證實了美國將進一步收緊對中國AI晶片及加速器出口的限制。這絕非巧合，而是大型機構投資者憑藉其強大的資訊網絡，提前洞悉政策風向，並在消息正式公佈前進行了大規模的避險與部位調整。摩根大通對聯電的巨額賣超，更印證了這股提前撤出的趨勢。與此同時，投信卻逆勢買進聯電、世芯-KY、創意，顯示內外資對此事件的解讀與策略存在顯著分歧。在拋售高風險AI晶片股的同時，外資轉而大買長榮航、華航等航空股，以及友達、群創等面板股，甚至連大立光、先進光等光學股也獲得青睞。這暗示著資金正從受地緣政治衝擊的AI供應鏈，轉向受惠於全球經濟復甦、通膨壓力緩解（如國際新聞二所示）的傳統景氣循環股或非AI科技股。自營商對緯創、廣達等伺服器相關股的賣超，或許也反映了對AI供應鏈前景的謹慎態度。外資的精準預判與大規模行動，無疑是今日市場最引人深思的「暴力聯結」。"
  }
}